math_round_af/__init__.py
math_round_af/main.py
math_round_af/test_main.py
math_round_af-1.0.3.dist-info/LICENSE
math_round_af-1.0.3.dist-info/METADATA
math_round_af-1.0.3.dist-info/WHEEL
math_round_af-1.0.3.dist-info/top_level.txt
math_round_af-1.0.3.dist-info/RECORD
