Metadata-Version: 2.1
Name: math-round-af
Version: 1.0.3
Summary: Python package that allows to get mathematically rounded floating numbers.
Home-page: https://github.com/AlbertFarkhutdinov/math_round_af
Author: Albert Farkhutdinov
Author-email: albertfarhutdinov@gmail.com
License: UNKNOWN
Platform: UNKNOWN
Classifier: Development Status :: 5 - Production/Stable
Classifier: Programming Language :: Python :: 3.9
Classifier: License :: OSI Approved :: MIT License
Classifier: Operating System :: OS Independent
Requires-Python: >=3.6
License-File: LICENSE
Requires-Dist: pytest (<8,>=6)
